Metadata-Version: 2.1
Name: odoo12-addon-shopinvader-cart-expiry
Version: 12.0.1.1.2
Summary: Shopinvader module to manage an expiry delay on cart
Home-page: http://www.shopinvader.com
Author: ACSONE SA/NV
License: AGPL-3
Platform: UNKNOWN
Classifier: Programming Language :: Python
Classifier: Framework :: Odoo
Classifier: License :: OSI Approved :: GNU Affero General Public License v3
Requires-Python: >=3.5
Requires-Dist: odoo12-addon-queue-job
Requires-Dist: odoo12-addon-shopinvader
Requires-Dist: odoo (<12.1dev,>=12.0a)
